highscore/__init__.py
highscore/core.py
highscore-0.0.1.dist-info/LICENSE
highscore-0.0.1.dist-info/METADATA
highscore-0.0.1.dist-info/WHEEL
highscore-0.0.1.dist-info/top_level.txt
highscore-0.0.1.dist-info/RECORD
